NiftiResampler/ResampleTools.py
NiftiResampler/__init__.py
NiftiResampler-0.1.1.dist-info/LICENSE.txt
NiftiResampler-0.1.1.dist-info/METADATA
NiftiResampler-0.1.1.dist-info/WHEEL
NiftiResampler-0.1.1.dist-info/top_level.txt
NiftiResampler-0.1.1.dist-info/RECORD
