Metadata-Version: 2.1
Name: NiftiResampler
Version: 0.1.1
Summary: Tools for reading dicom files, RT structures, and dose files, as well as tools for converting numpy prediction masks back to an RT structure
Home-page: https://github.com/brianmanderson/Resample_Class
Author: Brian Mark Anderson
Author-email: bmanderson@mdanderson.org
Classifier: Programming Language :: Python :: 3
Classifier: License :: OSI Approved :: GNU Affero General Public License v3
License-File: LICENSE.txt
Requires-Dist: numpy
Requires-Dist: SimpleITK
